{
  "data": [
    {
      "id": 102850,
      "task": {
        "id": 1384,
        "task_id": "A00291-012",
        "project_name": "AI Delivery",
        "project": 113,
        "task_name": "Development-Activity-Rohan",
        "is_active": true,
        "description": "AI delivery task",
        "status": "inprogress",
        "priority": "Low",
        "project_code": "INX00291",
        "assign_to": [310],
        "billing_type": "non-billable",
        "estimated_hours": null,
        "duration": null,
        "start_date": "2025-05-12",
        "end_date": null,
        "created_at": "2025-05-12T13:43:17.575684Z",
        "modified_at": "2026-01-08T05:31:44.548016Z",
        "deleted_at": null
      },
      "created_at": "2026-04-14T11:17:10.743558Z",
      "modified_at": null,
      "deleted_at": null,
      "is_active": true,
      "log_date": "2026-04-13",
      "log_time": "2:00:00",
      "work_description": "<ul><li><p>Take update from Parth Varecha about Connect DB refactoring and Review the code.</p></li><li><p>Practice React JS</p></li></ul>",
      "created_by": 310,
      "modified_by": null,
      "deleted_by": null,
      "user": 310,
      "log_hours": "2.00",
      "log_time_hours": 2,
      "log_time_minutes": 0,
      "hour_counter": 2,
      "min_counter": 0
    },
    {
      "id": 102849,
      "task": {
        "id": 1589,
        "task_id": "S00336-007",
        "project_name": "Solvere",
        "project": 158,
        "task_name": "Development Task - Rohan Movaliya",
        "is_active": true,
        "description": "",
        "status": "inprogress",
        "priority": "High",
        "project_code": "INX00336",
        "assign_to": [310],
        "billing_type": "non-billable",
        "estimated_hours": null,
        "duration": null,
        "start_date": null,
        "end_date": null,
        "created_at": "2025-10-21T05:32:28.568008Z",
        "modified_at": "2026-02-08T16:42:24.446901Z",
        "deleted_at": null
      },
      "created_at": "2026-04-14T11:15:35.138788Z",
      "modified_at": "2026-04-14T11:19:57.400813Z",
      "deleted_at": null,
      "is_active": true,
      "log_date": "2026-04-13",
      "log_time": "6:00:00",
      "work_description": "<ul><li><p>Run Service Module test cases and fix Errors and Failed Cases</p></li><li><p>Compare local .env, env.example and server .env file Compare among all and Create organized env.example file</p></li><li><p>Fix docker file as per updated .env file with hepl of Vaibhav Soni</p></li><li><p>Run all test case and create coverage report of all modules.</p></li><li><p>Docmented updated .env.example file</p></li></ul>",
      "created_by": 310,
      "modified_by": 310,
      "deleted_by": null,
      "user": 310,
      "log_hours": "6.00",
      "log_time_hours": 6,
      "log_time_minutes": 0,
      "hour_counter": 6,
      "min_counter": 0
    }
  ],
  "labels": {
    "total_hours": "8.00"
  }
}
